setup.py
couch_named_python/__init__.py
couch_named_python/base_io.py
couch_named_python/pyviews.py
couch_named_python.egg-info/PKG-INFO
couch_named_python.egg-info/SOURCES.txt
couch_named_python.egg-info/dependency_links.txt
couch_named_python.egg-info/entry_points.txt
couch_named_python.egg-info/top_level.txt