Metadata-Version: 1.0
Name: couch-named-python
Version: 0.1dev
Summary: CouchDB view server that executes functions on the python path by name
Home-page: https://github.com/danielrichman/couch-named-python
Author: Daniel Richman
Author-email: main@danielrichman.co.uk
License: GNU General Public License Version 3
Platform: UNKNOWN
